bump_version/__init__.py
bump_version/_version.py
bump_version/cli.py
bump_version/py.typed
bump_version/version_manager.py
bumpster-0.1.0.dist-info/METADATA
bumpster-0.1.0.dist-info/WHEEL
bumpster-0.1.0.dist-info/entry_points.txt
bumpster-0.1.0.dist-info/licenses/LICENSE
bumpster-0.1.0.dist-info/RECORD
