Metadata-Version: 2.4
Name: bumpster
Version: 0.1.0
Summary: A CLI tool for semantic version management
Project-URL: Homepage, https://github.com/yarnovo/bumpster-py
Project-URL: Repository, https://github.com/yarnovo/bumpster-py.git
Project-URL: Issues, https://github.com/yarnovo/bumpster-py/issues
Author: AI App Base
License: ISC
License-File: LICENSE
Requires-Python: >=3.12
Requires-Dist: click>=8.1.0
Requires-Dist: inquirer>=3.1.0
Requires-Dist: packaging>=23.0
Requires-Dist: rich>=13.0.0
Requires-Dist: tomlkit>=0.12.0
